jambot_plugin/__init__.py
jambot_plugin/bot_info.py
jambot_plugin/deps.py
jambot_plugin/handlers/__init__.py
jambot_plugin/handlers/base_handler.py
jambot_plugin/handlers/cron_handler.py
jambot_plugin/handlers/event_handler.py
jambot_plugin/handlers/http_handler.py
jambot_plugin/handlers/ping_handler.py
jambot_plugin/plugin.py
jambot_plugin/template.py
jambot_plugin/types.py
jambot_plugin/user_info.py
jambot_plugin-0.2.0.dist-info/WHEEL
jambot_plugin-0.2.0.dist-info/METADATA
jambot_plugin-0.2.0.dist-info/RECORD
