Metadata-Version: 2.1
Name: jambot-plugin
Version: 0.2.0
Summary: 
Author: Vladislav Bakaev
Author-email: vlad@bakaev.tech
Requires-Python: >=3.8,<4.0
Classifier: Programming Language :: Python :: 3
Classifier: Programming Language :: Python :: 3.10
Classifier: Programming Language :: Python :: 3.8
Classifier: Programming Language :: Python :: 3.9
Requires-Dist: ConfigArgParse (>=1.5.3,<2.0.0)
Requires-Dist: Jinja2 (>=3.0.3,<4.0.0)
Requires-Dist: aiodine (>=1.2.9,<2.0.0)
Requires-Dist: croniter (>=1.3.4,<2.0.0)
Requires-Dist: inflection (>=0.5.1,<0.6.0)
Requires-Dist: jambot-client (>=0.1.0,<0.2.0)
Requires-Dist: multidict (>=6.0.2,<7.0.0)
Requires-Dist: pydantic (>=1.9.0,<2.0.0)
